{
  "workshoptitle": "League of Legends Machine Learning with OCI - Introduction to Neural Networks",
  "help": "livelabs-help-db_us@oracle.com",
  "tutorials": [
    {
      "title": "Introduction",
      "description": "Introduction",
      "filename": "https://oracle-devrel.github.io/leagueoflegends-optimizer/hols/nn/intro/intro.md"
    },
    {
      "title": "Get Started",
      "description": "Prerequisites for LiveLabs (Oracle-owned tenancies). The title of the lab and the Contents Menu title (the title above) match for Prerequisite lab. This lab is always first.",
      "filename": "https://oracle-livelabs.github.io/common/labs/cloud-login/cloud-login.md"
    },
    {
      "title": "Lab 1: Infrastructure",
      "description": "Infrastructure",
      "filename": "https://oracle-devrel.github.io/leagueoflegends-optimizer/hols/nn/infra/infra.md"
    },
    {
      "title": "Lab 2: Understand Neural Networks",
      "description": "Understand Neural Networks",
      "filename": "https://oracle-devrel.github.io/leagueoflegends-optimizer/hols/nn/understand_nn/understand_nns.md"
    },
    {
      "title": "Lab 3: Build a Neural Network with fastai",
      "description": "Build a Neural Network with fastai",
      "filename": "https://oracle-devrel.github.io/leagueoflegends-optimizer/hols/nn/model_building/model_building.md"
    },
    {
      "title": "Need Help?",
      "description": "Solutions to Common Problems and Directions for Receiving Live Help",
      "filename": "https://oracle-livelabs.github.io/common/support/ocwsupportlab/ocwsupportlab.md"
    }
  ]
}
